chinillaclvm_tools/NodePath.py
chinillaclvm_tools/__init__.py
chinillaclvm_tools/binutils.py
chinillaclvm_tools/chinillaclvmc.py
chinillaclvm_tools/cmds.py
chinillaclvm_tools/curry.py
chinillaclvm_tools/debug.py
chinillaclvm_tools/operator_dict.py
chinillaclvm_tools/pattern_match.py
chinillaclvm_tools/py.typed
chinillaclvm_tools/sha256tree.py
chinillaclvm_tools/setuptools/__init__.py
chinillaclvm_tools/setuptools/build_chinillaclvm.py
chinillaclvm_tools/setuptools/patch_build_ext.py
chinillaclvm_tools/setuptools/patched_build_ext.py
ir/Type.py
ir/__init__.py
ir/py.typed
ir/reader.py
ir/utils.py
ir/writer.py
stages/__init__.py
stages/py.typed
stages/stage_0.py
stages/stage_2/__init__.py
stages/stage_2/bindings.py
stages/stage_2/compile.py
stages/stage_2/defaults.py
stages/stage_2/helpers.py
stages/stage_2/mod.py
stages/stage_2/operators.py
stages/stage_2/optimize.py
chinillaclvm_tools-0.4.7.dist-info/LICENSE
chinillaclvm_tools-0.4.7.dist-info/METADATA
chinillaclvm_tools-0.4.7.dist-info/WHEEL
chinillaclvm_tools-0.4.7.dist-info/entry_points.txt
chinillaclvm_tools-0.4.7.dist-info/top_level.txt
chinillaclvm_tools-0.4.7.dist-info/RECORD
