Metadata-Version: 2.1
Name: chinillaclvm-tools
Version: 0.4.7
Summary: CHINILLACLVM compiler.
Home-page: https://github.com/chinilla
Author: Chinilla Network, Inc.
Author-email: kiss@chinilla.net
License: https://opensource.org/licenses/Apache-2.0
Project-URL: Bug Reports, https://github.com/chinilla/chinillaclvm_tools
Project-URL: Source, https://github.com/chinilla/chinillaclvm_tools
Classifier: Development Status :: 3 - Alpha
Classifier: Programming Language :: Python :: 3
Classifier: Programming Language :: Python :: 3.6
Classifier: Programming Language :: Python :: 3.7
Classifier: License :: OSI Approved :: Apache Software License
Classifier: Topic :: Security :: Cryptography
License-File: LICENSE
Requires-Dist: chinillaclvm (>=0.9.2)
Provides-Extra: dev
Requires-Dist: pytest ; extra == 'dev'
